[
  {
    "name": "Jarro Magico 50° Negro Sin Caja Individual",
    "color": "negro",
    "price": 75,
    "genre": "unisex",
    "category": "jarros",
    "stock": 3,
    "size": ["11 oz (325ml)"],
    "image": "https://disershop.com.uy/cache//aadiser/productos/SU-JM-SC-550x550.jpg",
    "image2": "https://disershop.com.uy/cache/aadiser/productos/SU-JM-SC-2-550x550.jpg"
  },
  {
    "name": "Jarro glitter degrade plateado/ celeste",
    "color": "celeste",
    "price": 119,
    "genre": "unisex",
    "category": "jarros",
    "stock": 6,
    "size": ["11 oz (325ml)"],
    "image": "https://disershop.com.uy/cache/aadiser/productos/SU-MG-G-1418-550x550h.jpg",
    "image2": "https://disershop.com.uy/cache/aadiser/productos/SU-MG-G-1418-1-550x550h.jpg"
  },
  {
    "name": "Jarro sublimable cromolux manzana 11oz",
    "color": "manzana",
    "price": 119,
    "genre": "unisex",
    "category": "jarros",
    "stock": 3,
    "size": ["11 oz (325ml)"],
    "image": "https://disershop.com.uy/cache/aadiser/productos/SU-MGCH-20-2-550x550.jpg",
    "image2": "https://disershop.com.uy/cache/aadiser/productos/SU-MGCH-20-1-550x550.jpg"
  },
  {
    "name": "Jarro glitter degrade plateado/ celeste",
    "color": "celeste",
    "price": 119,
    "genre": "unisex",
    "category": "jarros",
    "stock": 6,
    "size": ["11 oz (325ml)"],
    "image": "https://disershop.com.uy/cache/aadiser/productos/SU-MG-G-1418-550x550h.jpg",
    "image2": "https://disershop.com.uy/cache/aadiser/productos/SU-MG-G-1418-1-550x550h.jpg"
  },
  {
    "name": "Jarro sublimable cromolux verde 11oz",
    "color": "verde",

    "price": 119,
    "genre": "unisex",
    "category": "jarros",
    "stock": 6,
    "size": ["11 oz (325ml)"],
    "image": "https://disershop.com.uy/cache/aadiser/productos/SU-MGCH-08-2-550x550.jpg",
    "image2": "https://disershop.com.uy/cache/aadiser/productos/SU-MGCH-08-1-550x550.jpg"
  },
  {
    "name": "Jarro glitter degrade plateado/ celeste",
    "color": "celeste",
    "price": 119,
    "genre": "unisex",
    "category": "jarros",
    "stock": 6,
    "size": ["11 oz (325ml)"],
    "image": "https://disershop.com.uy/cache/aadiser/productos/SU-MG-G-1418-550x550h.jpg",
    "image2": "https://disershop.com.uy/cache/aadiser/productos/SU-MG-G-1418-1-550x550h.jpg"
  },
  {
    "name": "Jarro Magico 50° Negro Sin Caja Individual",
    "color": "negro",
    "price": 75,
    "genre": "unisex",
    "category": "jarros",
    "stock": 3,
    "size": ["11 oz (325ml)"],
    "image": "https://disershop.com.uy/cache//aadiser/productos/SU-JM-SC-550x550.jpg",
    "image2": "https://disershop.com.uy/cache/aadiser/productos/SU-JM-SC-2-550x550.jpg"
  },
  {
    "name": "Jarro sublimable cromolux manzana 11oz",
    "color": "manzana",
    "price": 119,
    "genre": "unisex",
    "category": "jarros",
    "stock": 3,
    "size": ["11 oz (325ml)"],
    "image": "https://disershop.com.uy/cache/aadiser/productos/SU-MGCH-20-2-550x550.jpg",
    "image2": "https://disershop.com.uy/cache/aadiser/productos/SU-MGCH-20-1-550x550.jpg"
  },
  {
    "name": "Jarro sublimable cromolux verde 11oz",
    "color": "verde",

    "price": 119,
    "genre": "unisex",
    "category": "jarros",
    "stock": 6,
    "size": ["11 oz (325ml)"],
    "image": "https://disershop.com.uy/cache/aadiser/productos/SU-MGCH-08-2-550x550.jpg",
    "image2": "https://disershop.com.uy/cache/aadiser/productos/SU-MGCH-08-1-550x550.jpg"
  },
  {
    "name": "Jarro Magico 50° Negro Sin Caja Individual",
    "color": "negro",
    "price": 75,
    "genre": "unisex",
    "category": "jarros",
    "stock": 3,
    "size": ["11 oz (325ml)"],
    "image": "https://disershop.com.uy/cache//aadiser/productos/SU-JM-SC-550x550.jpg",
    "image2": "https://disershop.com.uy/cache/aadiser/productos/SU-JM-SC-2-550x550.jpg"
  },
  {
    "name": "Jarro sublimable cromolux manzana 11oz",
    "color": "manzana",
    "price": 119,
    "genre": "unisex",
    "category": "jarros",
    "stock": 3,
    "size": ["11 oz (325ml)"],
    "image": "https://disershop.com.uy/cache/aadiser/productos/SU-MGCH-20-2-550x550.jpg",
    "image2": "https://disershop.com.uy/cache/aadiser/productos/SU-MGCH-20-1-550x550.jpg"
  },
  {
    "name": "Jarro sublimable cromolux verde 11oz",
    "color": "verde",

    "price": 119,
    "genre": "unisex",
    "category": "jarros",
    "stock": 6,
    "size": ["11 oz (325ml)"],
    "image": "https://disershop.com.uy/cache/aadiser/productos/SU-MGCH-08-2-550x550.jpg",
    "image2": "https://disershop.com.uy/cache/aadiser/productos/SU-MGCH-08-1-550x550.jpg"
  },
  {
    "name": "Jarro Magico 50° Negro Sin Caja Individual",
    "color": "negro",
    "price": 75,
    "genre": "unisex",
    "category": "jarros",
    "stock": 3,
    "size": ["11 oz (325ml)"],
    "image": "https://disershop.com.uy/cache//aadiser/productos/SU-JM-SC-550x550.jpg",
    "image2": "https://disershop.com.uy/cache/aadiser/productos/SU-JM-SC-2-550x550.jpg"
  },
  {
    "name": "Jarro sublimable cromolux manzana 11oz",
    "color": "manzana",
    "price": 119,
    "genre": "unisex",
    "category": "jarros",
    "stock": 3,
    "size": ["11 oz (325ml)"],
    "image": "https://disershop.com.uy/cache/aadiser/productos/SU-MGCH-20-2-550x550.jpg",
    "image2": "https://disershop.com.uy/cache/aadiser/productos/SU-MGCH-20-1-550x550.jpg"
  },
  {
    "name": "Jarro sublimable cromolux verde 11oz",
    "color": "verde",

    "price": 119,
    "genre": "unisex",
    "category": "jarros",
    "stock": 6,
    "size": ["11 oz (325ml)"],
    "image": "https://disershop.com.uy/cache/aadiser/productos/SU-MGCH-08-2-550x550.jpg",
    "image2": "https://disershop.com.uy/cache/aadiser/productos/SU-MGCH-08-1-550x550.jpg"
  },
  {
    "name": "Jarro Magico 50° Negro Sin Caja Individual",
    "color": "negro",
    "price": 75,
    "genre": "unisex",
    "category": "jarros",
    "stock": 3,
    "size": ["11 oz (325ml)"],
    "image": "https://disershop.com.uy/cache//aadiser/productos/SU-JM-SC-550x550.jpg",
    "image2": "https://disershop.com.uy/cache/aadiser/productos/SU-JM-SC-2-550x550.jpg"
  },
  {
    "name": "Jarro sublimable cromolux manzana 11oz",
    "color": "manzana",
    "price": 119,
    "genre": "unisex",
    "category": "jarros",
    "stock": 3,
    "size": ["11 oz (325ml)"],
    "image": "https://disershop.com.uy/cache/aadiser/productos/SU-MGCH-20-2-550x550.jpg",
    "image2": "https://disershop.com.uy/cache/aadiser/productos/SU-MGCH-20-1-550x550.jpg"
  },
  {
    "name": "Jarro glitter degrade plateado/ celeste",
    "color": "celeste",
    "price": 119,
    "genre": "unisex",
    "category": "jarros",
    "stock": 6,
    "size": ["11 oz (325ml)"],
    "image": "https://disershop.com.uy/cache/aadiser/productos/SU-MG-G-1418-550x550h.jpg",
    "image2": "https://disershop.com.uy/cache/aadiser/productos/SU-MG-G-1418-1-550x550h.jpg"
  },
  {
    "name": "Jarro sublimable cromolux verde 11oz",
    "color": "verde",

    "price": 119,
    "genre": "unisex",
    "category": "jarros",
    "stock": 6,
    "size": ["11 oz (325ml)"],
    "image": "https://disershop.com.uy/cache/aadiser/productos/SU-MGCH-08-2-550x550.jpg",
    "image2": "https://disershop.com.uy/cache/aadiser/productos/SU-MGCH-08-1-550x550.jpg"
  },
  {
    "name": "Jarro Magico 50° Negro Sin Caja Individual",
    "color": "negro",
    "price": 75,
    "genre": "unisex",
    "category": "jarros",
    "stock": 3,
    "capacity": "12 oz (325ml)",
    "image": "https://disershop.com.uy/cache//aadiser/productos/SU-JM-SC-550x550.jpg",
    "image2": "https://disershop.com.uy/cache/aadiser/productos/SU-JM-SC-2-550x550.jpg"
  },
  {
    "name": "Jarro sublimable cromolux manzana 11oz",
    "color": "manzana",
    "price": 119,
    "genre": "unisex",
    "category": "jarros",
    "stock": 3,
    "capacity": "15 oz (325ml)",
    "image": "https://disershop.com.uy/cache/aadiser/productos/SU-MGCH-20-2-550x550.jpg",
    "image2": "https://disershop.com.uy/cache/aadiser/productos/SU-MGCH-20-1-550x550.jpg"
  },
  {
    "name": "Jarro sublimable cromolux verde 11oz",
    "color": "verde",

    "price": 119,
    "genre": "unisex",
    "category": "jarros",
    "capacity": "15 oz (325ml)",
    "stock": 6,
    "size": ["11 oz (325ml)"],
    "image": "https://disershop.com.uy/cache/aadiser/productos/SU-MGCH-08-2-550x550.jpg",
    "image2": "https://disershop.com.uy/cache/aadiser/productos/SU-MGCH-08-1-550x550.jpg"
  },
  {
    "name": "Jarro Magico 50° Negro Sin Caja Individual",
    "color": "negro",
    "price": 75,
    "genre": "unisex",
    "category": "jarros",
    "capacity": "15 oz (325ml)",
    "stock": 3,
    "size": ["11 oz (325ml)"],
    "image": "https://disershop.com.uy/cache//aadiser/productos/SU-JM-SC-550x550.jpg",
    "image2": "https://disershop.com.uy/cache/aadiser/productos/SU-JM-SC-2-550x550.jpg"
  },
  {
    "name": "Jarro sublimable cromolux manzana 11oz",
    "color": "manzana",
    "price": 119,
    "genre": "unisex",
    "category": "jarros",
    "capacity": "15 oz (325ml)",
    "stock": 3,
    "size": ["11 oz (325ml)"],
    "image": "https://disershop.com.uy/cache/aadiser/productos/SU-MGCH-20-2-550x550.jpg",
    "image2": "https://disershop.com.uy/cache/aadiser/productos/SU-MGCH-20-1-550x550.jpg"
  },
  {
    "name": "Jarro sublimable cromolux verde 11oz",
    "color": "verde",

    "price": 119,
    "genre": "unisex",
    "category": "jarros",
    "stock": 6,
    "size": ["11 oz (325ml)"],
    "image": "https://disershop.com.uy/cache/aadiser/productos/SU-MGCH-08-2-550x550.jpg",
    "image2": "https://disershop.com.uy/cache/aadiser/productos/SU-MGCH-08-1-550x550.jpg"
  },
  {
    "name": "Jarro Magico 50° Negro Sin Caja Individual",
    "color": "negro",
    "price": 75,
    "genre": "unisex",
    "category": "jarros",
    "stock": 3,
    "capacity": "25 oz (325ml)",
    "size": ["11 oz (325ml)"],
    "image": "https://disershop.com.uy/cache//aadiser/productos/SU-JM-SC-550x550.jpg",
    "image2": "https://disershop.com.uy/cache/aadiser/productos/SU-JM-SC-2-550x550.jpg"
  },
  {
    "name": "Jarro sublimable cromolux manzana 11oz",
    "color": "manzana",
    "price": 119,
    "genre": "unisex",
    "category": "jarros",
    "capacity": "27 oz (325ml)",
    "stock": 3,
    "size": ["11 oz (325ml)"],
    "image": "https://disershop.com.uy/cache/aadiser/productos/SU-MGCH-20-2-550x550.jpg",
    "image2": "https://disershop.com.uy/cache/aadiser/productos/SU-MGCH-20-1-550x550.jpg"
  },
  {
    "name": "Jarro sublimable cromolux verde 11oz",
    "color": "verde",

    "price": 119,
    "genre": "unisex",
    "category": "jarros",
    "stock": 6,
    "size": ["11 oz (325ml)"],
    "image": "https://disershop.com.uy/cache/aadiser/productos/SU-MGCH-08-2-550x550.jpg",
    "image2": "https://disershop.com.uy/cache/aadiser/productos/SU-MGCH-08-1-550x550.jpg"
  },
  {
    "name": "Jarro glitter degrade plateado/ celeste",
    "color": "celeste",
    "price": 119,
    "genre": "unisex",
    "category": "jarros",
    "stock": 6,
    "size": ["11 oz (325ml)"],
    "image": "https://disershop.com.uy/cache/aadiser/productos/SU-MG-G-1418-550x550h.jpg",
    "image2": "https://disershop.com.uy/cache/aadiser/productos/SU-MG-G-1418-1-550x550h.jpg"
  },
  {
    "name": "Jarro Magico 50° Negro Sin Caja Individual",
    "color": "negro",
    "price": 75,
    "genre": "unisex",
    "category": "jarros",
    "stock": 3,
    "size": ["11 oz (325ml)"],
    "image": "https://disershop.com.uy/cache//aadiser/productos/SU-JM-SC-550x550.jpg",
    "image2": "https://disershop.com.uy/cache/aadiser/productos/SU-JM-SC-2-550x550.jpg"
  },
  {
    "name": "Jarro glitter degrade plateado/ celeste",
    "color": "celeste",
    "price": 119,
    "genre": "unisex",
    "category": "jarros",
    "stock": 6,
    "size": ["11 oz (325ml)"],
    "image": "https://disershop.com.uy/cache/aadiser/productos/SU-MG-G-1418-550x550h.jpg",
    "image2": "https://disershop.com.uy/cache/aadiser/productos/SU-MG-G-1418-1-550x550h.jpg"
  },
  {
    "name": "Jarro sublimable cromolux manzana 11oz",
    "color": "manzana",
    "price": 119,
    "genre": "unisex",
    "category": "jarros",
    "stock": 3,
    "size": ["11 oz (325ml)"],
    "image": "https://disershop.com.uy/cache/aadiser/productos/SU-MGCH-20-2-550x550.jpg",
    "image2": "https://disershop.com.uy/cache/aadiser/productos/SU-MGCH-20-1-550x550.jpg"
  },
  {
    "name": "Jarro sublimable cromolux verde 11oz",
    "color": "verde",

    "price": 119,
    "genre": "unisex",
    "category": "jarros",
    "stock": 6,
    "size": ["11 oz (325ml)"],
    "image": "https://disershop.com.uy/cache/aadiser/productos/SU-MGCH-08-2-550x550.jpg",
    "image2": "https://disershop.com.uy/cache/aadiser/productos/SU-MGCH-08-1-550x550.jpg"
  },
  {
    "name": "Jarro Magico 50° Negro Sin Caja Individual",
    "color": "negro",
    "price": 75,
    "genre": "unisex",
    "category": "jarros",
    "stock": 3,
    "size": ["11 oz (325ml)"],
    "image": "https://disershop.com.uy/cache//aadiser/productos/SU-JM-SC-550x550.jpg",
    "image2": "https://disershop.com.uy/cache/aadiser/productos/SU-JM-SC-2-550x550.jpg"
  },
  {
    "name": "Jarro sublimable cromolux manzana 11oz",
    "color": "manzana",
    "price": 119,
    "genre": "unisex",
    "category": "jarros",
    "stock": 3,
    "size": ["11 oz (325ml)"],
    "image": "https://disershop.com.uy/cache/aadiser/productos/SU-MGCH-20-2-550x550.jpg",
    "image2": "https://disershop.com.uy/cache/aadiser/productos/SU-MGCH-20-1-550x550.jpg"
  },
  {
    "name": "Jarro sublimable cromolux verde 11oz",
    "color": "verde",

    "price": 119,
    "genre": "unisex",
    "category": "jarros",
    "stock": 6,
    "size": ["11 oz (325ml)"],
    "image": "https://disershop.com.uy/cache/aadiser/productos/SU-MGCH-08-2-550x550.jpg",
    "image2": "https://disershop.com.uy/cache/aadiser/productos/SU-MGCH-08-1-550x550.jpg"
  },
  {
    "name": "Jarro Magico 50° Negro Sin Caja Individual",
    "color": "negro",
    "price": 75,
    "genre": "unisex",
    "category": "jarros",
    "stock": 3,
    "size": ["11 oz (325ml)"],
    "image": "https://disershop.com.uy/cache//aadiser/productos/SU-JM-SC-550x550.jpg",
    "image2": "https://disershop.com.uy/cache/aadiser/productos/SU-JM-SC-2-550x550.jpg"
  },
  {
    "name": "Jarro sublimable cromolux manzana 11oz",
    "color": "manzana",
    "price": 119,
    "genre": "unisex",
    "category": "jarros",
    "stock": 3,
    "size": ["11 oz (325ml)"],
    "image": "https://disershop.com.uy/cache/aadiser/productos/SU-MGCH-20-2-550x550.jpg",
    "image2": "https://disershop.com.uy/cache/aadiser/productos/SU-MGCH-20-1-550x550.jpg"
  },
  {
    "name": "Jarro sublimable cromolux verde 11oz",
    "color": "verde",

    "price": 119,
    "genre": "unisex",
    "category": "jarros",
    "stock": 6,
    "size": ["11 oz (325ml)"],
    "image": "https://disershop.com.uy/cache/aadiser/productos/SU-MGCH-08-2-550x550.jpg",
    "image2": "https://disershop.com.uy/cache/aadiser/productos/SU-MGCH-08-1-550x550.jpg"
  },
  {
    "name": "Jarro Magico 50° Negro Sin Caja Individual",
    "color": "negro",
    "price": 75,
    "genre": "unisex",
    "category": "jarros",
    "stock": 3,
    "size": ["11 oz (325ml)"],
    "image": "https://disershop.com.uy/cache//aadiser/productos/SU-JM-SC-550x550.jpg",
    "image2": "https://disershop.com.uy/cache/aadiser/productos/SU-JM-SC-2-550x550.jpg"
  },
  {
    "name": "Jarro sublimable cromolux manzana 11oz",
    "color": "manzana",
    "price": 119,
    "genre": "unisex",
    "category": "jarros",
    "stock": 3,
    "size": ["11 oz (325ml)"],
    "image": "https://disershop.com.uy/cache/aadiser/productos/SU-MGCH-20-2-550x550.jpg",
    "image2": "https://disershop.com.uy/cache/aadiser/productos/SU-MGCH-20-1-550x550.jpg"
  },
  {
    "name": "Jarro sublimable cromolux verde 11oz",
    "color": "verde",

    "price": 119,
    "genre": "unisex",
    "category": "jarros",
    "stock": 6,
    "size": ["11 oz (325ml)"],
    "image": "https://disershop.com.uy/cache/aadiser/productos/SU-MGCH-08-2-550x550.jpg",
    "image2": "https://disershop.com.uy/cache/aadiser/productos/SU-MGCH-08-1-550x550.jpg"
  },
  {
    "name": "Jarro Magico 50° Negro Sin Caja Individual",
    "color": "negro",
    "price": 75,
    "genre": "unisex",
    "category": "jarros",
    "stock": 3,
    "size": ["11 oz (325ml)"],
    "image": "https://disershop.com.uy/cache//aadiser/productos/SU-JM-SC-550x550.jpg",
    "image2": "https://disershop.com.uy/cache/aadiser/productos/SU-JM-SC-2-550x550.jpg"
  },
  {
    "name": "Jarro sublimable cromolux manzana 11oz",
    "color": "manzana",
    "price": 119,
    "genre": "unisex",
    "category": "jarros",
    "stock": 3,
    "size": ["11 oz (325ml)"],
    "image": "https://disershop.com.uy/cache/aadiser/productos/SU-MGCH-20-2-550x550.jpg",
    "image2": "https://disershop.com.uy/cache/aadiser/productos/SU-MGCH-20-1-550x550.jpg"
  },
  {
    "name": "Jarro sublimable cromolux verde 11oz",
    "color": "verde",

    "price": 119,
    "genre": "unisex",
    "category": "jarros",
    "stock": 6,
    "size": ["11 oz (325ml)"],
    "image": "https://disershop.com.uy/cache/aadiser/productos/SU-MGCH-08-2-550x550.jpg",
    "image2": "https://disershop.com.uy/cache/aadiser/productos/SU-MGCH-08-1-550x550.jpg"
  },
  {
    "name": "Jarro Magico 50° Negro Sin Caja Individual",
    "color": "negro",
    "price": 75,
    "genre": "unisex",
    "category": "jarros",
    "stock": 3,
    "size": ["11 oz (325ml)"],
    "image": "https://disershop.com.uy/cache//aadiser/productos/SU-JM-SC-550x550.jpg",
    "image2": "https://disershop.com.uy/cache/aadiser/productos/SU-JM-SC-2-550x550.jpg"
  },
  {
    "name": "Jarro sublimable cromolux manzana 11oz",
    "color": "manzana",
    "price": 119,
    "genre": "unisex",
    "category": "jarros",
    "stock": 3,
    "size": ["11 oz (325ml)"],
    "image": "https://disershop.com.uy/cache/aadiser/productos/SU-MGCH-20-2-550x550.jpg",
    "image2": "https://disershop.com.uy/cache/aadiser/productos/SU-MGCH-20-1-550x550.jpg"
  },
  {
    "name": "Jarro sublimable cromolux verde 11oz",
    "color": "verde",

    "price": 119,
    "genre": "unisex",
    "category": "jarros",
    "stock": 6,
    "size": ["11 oz (325ml)"],
    "image": "https://disershop.com.uy/cache/aadiser/productos/SU-MGCH-08-2-550x550.jpg",
    "image2": "https://disershop.com.uy/cache/aadiser/productos/SU-MGCH-08-1-550x550.jpg"
  },
  {
    "name": "Jarro Magico 50° Negro Sin Caja Individual",
    "color": "negro",
    "price": 75,
    "genre": "unisex",
    "category": "jarros",
    "stock": 3,
    "size": ["11 oz (325ml)"],
    "image": "https://disershop.com.uy/cache//aadiser/productos/SU-JM-SC-550x550.jpg",
    "image2": "https://disershop.com.uy/cache/aadiser/productos/SU-JM-SC-2-550x550.jpg"
  },
  {
    "name": "Jarro sublimable cromolux manzana 11oz",
    "color": "manzana",
    "price": 119,
    "genre": "unisex",
    "category": "jarros",
    "stock": 3,
    "size": ["11 oz (325ml)"],
    "image": "https://disershop.com.uy/cache/aadiser/productos/SU-MGCH-20-2-550x550.jpg",
    "image2": "https://disershop.com.uy/cache/aadiser/productos/SU-MGCH-20-1-550x550.jpg"
  },
  {
    "name": "Jarro sublimable cromolux verde 11oz",
    "color": "verde",

    "price": 119,
    "genre": "unisex",
    "category": "jarros",
    "stock": 6,
    "size": ["11 oz (325ml)"],
    "image": "https://disershop.com.uy/cache/aadiser/productos/SU-MGCH-08-2-550x550.jpg",
    "image2": "https://disershop.com.uy/cache/aadiser/productos/SU-MGCH-08-1-550x550.jpg"
  },
  {
    "name": "Jarro Magico 50° Negro Sin Caja Individual",
    "color": "negro",
    "price": 75,
    "genre": "unisex",
    "category": "jarros",
    "stock": 3,
    "size": ["11 oz (325ml)"],
    "image": "https://disershop.com.uy/cache//aadiser/productos/SU-JM-SC-550x550.jpg",
    "image2": "https://disershop.com.uy/cache/aadiser/productos/SU-JM-SC-2-550x550.jpg"
  },
  {
    "name": "Jarro sublimable cromolux manzana 11oz",
    "color": "manzana",
    "price": 119,
    "genre": "unisex",
    "category": "jarros",
    "stock": 3,
    "size": ["11 oz (325ml)"],
    "image": "https://disershop.com.uy/cache/aadiser/productos/SU-MGCH-20-2-550x550.jpg",
    "image2": "https://disershop.com.uy/cache/aadiser/productos/SU-MGCH-20-1-550x550.jpg"
  },
  {
    "name": "Jarro sublimable cromolux verde 11oz",
    "color": "verde",

    "price": 119,
    "genre": "unisex",
    "category": "jarros",
    "stock": 6,
    "size": ["11 oz (325ml)"],
    "image": "https://disershop.com.uy/cache/aadiser/productos/SU-MGCH-08-2-550x550.jpg",
    "image2": "https://disershop.com.uy/cache/aadiser/productos/SU-MGCH-08-1-550x550.jpg"
  },
  {
    "name": "Jarro Magico 50° Negro Sin Caja Individual",
    "color": "negro",
    "price": 75,
    "genre": "unisex",
    "category": "jarros",
    "stock": 3,
    "size": ["11 oz (325ml)"],
    "image": "https://disershop.com.uy/cache//aadiser/productos/SU-JM-SC-550x550.jpg",
    "image2": "https://disershop.com.uy/cache/aadiser/productos/SU-JM-SC-2-550x550.jpg"
  },
  {
    "name": "Jarro sublimable cromolux manzana 11oz",
    "color": "manzana",
    "price": 119,
    "genre": "unisex",
    "category": "jarros",
    "stock": 3,
    "size": ["11 oz (325ml)"],
    "image": "https://disershop.com.uy/cache/aadiser/productos/SU-MGCH-20-2-550x550.jpg",
    "image2": "https://disershop.com.uy/cache/aadiser/productos/SU-MGCH-20-1-550x550.jpg"
  },
  {
    "name": "Jarro sublimable cromolux verde 11oz",
    "color": "verde",

    "price": 119,
    "genre": "unisex",
    "category": "jarros",
    "stock": 6,
    "size": ["11 oz (325ml)"],
    "image": "https://disershop.com.uy/cache/aadiser/productos/SU-MGCH-08-2-550x550.jpg",
    "image2": "https://disershop.com.uy/cache/aadiser/productos/SU-MGCH-08-1-550x550.jpg"
  },
  {
    "name": "Jarro Magico 50° Negro Sin Caja Individual",
    "color": "negro",
    "price": 75,
    "genre": "unisex",
    "category": "jarros",
    "stock": 3,
    "size": ["11 oz (325ml)"],
    "image": "https://disershop.com.uy/cache//aadiser/productos/SU-JM-SC-550x550.jpg",
    "image2": "https://disershop.com.uy/cache/aadiser/productos/SU-JM-SC-2-550x550.jpg"
  },
  {
    "name": "Jarro sublimable cromolux manzana 11oz",
    "color": "manzana",
    "price": 119,
    "genre": "unisex",
    "category": "jarros",
    "stock": 3,
    "size": ["11 oz (325ml)"],
    "image": "https://disershop.com.uy/cache/aadiser/productos/SU-MGCH-20-2-550x550.jpg",
    "image2": "https://disershop.com.uy/cache/aadiser/productos/SU-MGCH-20-1-550x550.jpg"
  },
  {
    "name": "Jarro glitter degrade plateado/ celeste",
    "color": "celeste",
    "price": 119,
    "genre": "unisex",
    "category": "jarros",
    "stock": 6,
    "size": ["11 oz (325ml)"],
    "image": "https://disershop.com.uy/cache/aadiser/productos/SU-MG-G-1418-550x550h.jpg",
    "image2": "https://disershop.com.uy/cache/aadiser/productos/SU-MG-G-1418-1-550x550h.jpg"
  }
]
